<root><simulation><result_generated_time />2023-05-17 20:22:52<layer><layer_spec />{'B': 1, 'K': 256, 'C': 256, 'OY': 14, 'OX': 14, 'IY': 16, 'IX': 16, 'FY': 3, 'FX': 3, 'SY': 1, 'SX': 1, 'SFY': 1, 'SFX': 1, 'G': 1}<im2col_enable />False<total_MAC_operation />115605504<total_data_size_element />{'W': 589824, 'I': 65536, 'O': 50176}<total_data_reuse />{'W': 196, 'I': 1764.0, 'O': 2304}</layer><search_engine><mem_hierarchy_search><mode />fixed<mem_scheme_index />1/1</mem_hierarchy_search><spatial_mapping_search><mode />greedy mapping with hint<spatial_utilization_threshold />0.0<unrolling_scheme_index />1/2</spatial_mapping_search><temporal_mapping_search><mode />loma search<valid_temporal_mapping_found />10080</temporal_mapping_search></search_engine><hw_spec><PE_array><precision_bit />{'W': 8, 'I': 8, 'O_partial': 8, 'O_final': 8}<MAC_array_size />{'Col': 30, 'Row': 32}</PE_array><memory_hierarchy><mem_name_in_the_hierarchy><W />['spad_32byte', 'buffer_2Mbyte', 'sram_big']<I />['spad_32byte', 'buffer_2Mbyte', 'sram_big']<O />['spad_32byte', 'buffer_2Mbyte', 'sram_big']</mem_name_in_the_hierarchy><mem_size_bit />{'W': [512, 25165824, 34359738368], 'I': [512, 25165824, 34359738368], 'O': [512, 25165824, 34359738368]}<mem_bw_bit_per_cycle_or_mem_wordlength />{'W': [[64, 64], [384, 384], [2048, 2048]], 'I': [[64, 64], [384, 384], [2048, 2048]], 'O': [[64, 64], [384, 384], [2048, 2048]]}<mem_access_energy_per_word />{'W': [[0.000336027, 0.000364555], [0.07895925, 0.0696813], [1.33185, 1.33185]], 'I': [[0.000336027, 0.000364555], [0.07895925, 0.0696813], [1.33185, 1.33185]], 'O': [[0.000336027, 0.000364555], [0.07895925, 0.0696813], [1.33185, 1.33185]]}<mem_type />{'W': ['dp_sb', 'dp_db', 'dp_sb'], 'I': ['dp_sb', 'dp_db', 'dp_sb'], 'O': ['dp_sb', 'dp_db', 'dp_sb']}<mem_share />{0: [('W', 'sram_big'), ('I', 'sram_big'), ('O', 'sram_big')], 1: [('W', 'buffer_2Mbyte'), ('I', 'buffer_2Mbyte'), ('O', 'buffer_2Mbyte')]}<mem_area_single_module />{'W': [0.000693826, 20.258474999999997, 93.2871], 'I': [0.000693826, 20.258474999999997, 93.2871], 'O': [0.000693826, 20.258474999999997, 93.2871]}<mem_unroll />{'W': [1, 1, 1], 'I': [960, 1, 1], 'O': [960, 1, 1]}</memory_hierarchy></hw_spec><results><basic_info><spatial_unrolling><W />[[[('OX', 30)], [('OY', 32)]], [], [], []]<I />[[], [[('OX', 30)], [('OY', 32)]], [], []]<O />[[], [[('OX', 30)], [('OY', 32)]], [], []]<greedy_mapping />True<footer_info />{'B': 0, 'K': 0, 'C': 0, 'OY': 14, 'OX': 14, 'FY': 0, 'FX': 0}</spatial_unrolling><temporal_mapping><W />[[('K', 16), ('C', 4)], [('C', 4), ('K', 4), ('C', 16), ('FX', 3), ('FY', 3), ('K', 4)], []]<I />[[('K', 16), ('C', 4), ('C', 4), ('K', 4)], [('C', 16), ('FX', 3), ('FY', 3), ('K', 4)], []]<O />[[('K', 16), ('C', 4), ('C', 4), ('K', 4), ('C', 16), ('FX', 3), ('FY', 3)], [('K', 4)], []]<fully_PE_level_output_stationary />True</temporal_mapping><data_reuse />{'W': [196.0, 1, 1, 1], 'I': [1.0, 64.0, 27.56, 1.0], 'O': [1.0, 2304, 1, 1]}<I_pr_diagonally_broadcast_or_fifo_effect />'I': [False, False, False, False]<used_mem_size_bit />{'W': [512, 4718592, 4718592], 'I': [128, 524288, 524288], 'O': [512, 401408, 401408], 'O_partial': [512, 0, 0], 'O_final': [0, 401408, 401408]}<actual_mem_utilization_individual />{'W': [1.0, 0.19, 0.0], 'I': [0.25, 0.09, 0.0], 'O': [1.0, 0.08, 0.0]}<actual_mem_utilization_shared />{'W': [1.0, 0.35, 0.0], 'I': [0.25, 0.35, 0.0], 'O': [1.0, 0.35, 0.0]}<effective_mem_size_bit />{'W': [32, 1179648, 4718592], 'I': [128, 524288, 524288], 'O': [512, 100352, 401408], 'O_partial': [512, 0, 0], 'O_final': [0, 100352, 401408]}<total_unit_count />{'W': [960, 1, 1, 1], 'I': [960, 960, 1, 1], 'O': [960, 960, 1, 1]}<unique_unit_count />{'W': [1, 1, 1, 1], 'I': [960, 960, 1, 1], 'O': [960, 960, 1, 1]}<duplicate_unit_count />{'W': [960.0, 1.0, 1.0, 1.0], 'I': [1.0, 1.0, 1.0, 1.0], 'O': [1.0, 1.0, 1.0, 1.0]}<mem_access_count_elem><W />[[589824, 589824], [589824, 589824], [589824, 0]]<I />[[7225344, 1806336], [8847360, 65536], [65536, 0]]<O />[[(115555328, 115605504), (50176, 0)], [(0, 245760), (50176, 0)], [(0, 50176), (0, 0)]]<O_partial />[[(115555328, 115605504), (0, 0)], [(0, 0), (0, 0)], [(0, 0), (0, 0)]]<O_final />[[(0, 0), (50176, 0)], [(0, 245760), (50176, 0)], [(0, 50176), (0, 0)]]</mem_access_count_elem><mem_access_count_word><W />[[73728, 73728], [12288, 12288], [2304, 0]]<I />[[903168, 225792], [184320, 1365], [256, 0]]<O />[[(14444416, 14450688), (6272, 0)], [(0, 5120), (1045, 0)], [(0, 196), (0, 0)]]<O_partial />[([14444416, 14450688], [0, 0]), ([0, 0], [0, 0]), ([0, 0], [0, 0])]<O_final />[([0, 0], [6272, 0]), ([0, 5120], [1045, 0]), ([0, 196], [0, 0])]</mem_access_count_word><mac_count><active />115605504<idle />450625536</mac_count></basic_info><energy><total_energy />275276055.2<mem_energy_breakdown><W />[51.7, 1826.5, 3068.6]<I />[385.8, 14648.9, 341.0]<O />[10123.9, 439.3, 261.0]</mem_energy_breakdown><MAC_energy><active_MAC />252713631.7<idle_MAC />22531276.8<total />275244908.5</MAC_energy></energy><performance><mac_array_utilization><utilization_with_data_loading />0.1978<utilization_without_data_loading />0.2038<utilization_spatial />0.2042<utilization_temporal_with_data_loading />0.9686<mac_utilize_temporal_without_data_loading />0.9983</mac_array_utilization><latency><latency_cycle_with_data_loading />608947<latency_cycle_without_data_loading />590848<ideal_computing_cycle />589824<data_loading><load_cycle_total />18099<load_cycle_individual />{'W': [8, 12288, 0], 'I': [320, 5803, 0]}<load_cycle_combined />{'W': 12288, 'I': 5803}</data_loading><mem_stalling><mem_stall_cycle_total />1024<mem_stall_cycle_individual />{'W': [[-589823], [-516040, -580545], [-589824, -589824]], 'I': [[-589823], [-587650, -404800], [-589824, -589824]], 'O': [[-589824], [-4064, 1024], [-584704, -588864]]}<mem_stall_cycle_shared />{'W': [[-589823], [-516040, 0], [0, 0]], 'I': [[-589823], [-587650, 0], [0, 0]], 'O': [[-589824], [-4064, 1024], [-584704, -588864]]}<latency_deep_analysis><data_size_each_level_unrolled />{'W': [512, 4718592, 4718592], 'I': [128, 524288, 524288], 'O': [512, 401408, 401408], 'O_partial': [512, 0, 0], 'O_final': [0, 401408, 401408]}<data_size_each_level_total />{'W': [512, 4718592, 4718592], 'I': [122880, 524288, 524288], 'O': [491520, 401408, 401408]}<loop_cycles_each_level />{'W': [64, 589824, 589824], 'I': [1024, 589824, 589824], 'O': [147456, 589824, 589824]}<top_ir_loop_size />{'W': [1, 1, 1], 'I': [4, 36, 1], 'O': [144, 1, 1]}<req_aver_mem_bw />{'W': [[8.0, 8.0], [8.0, 8.0], [8.0, 8.0]], 'I': [[8.0, 0.1], [120.0, 3.8], [3.8, 3.8]], 'O': [[8.0, 0.0], [3.3, 3.3], [3.3, 3.3]]}<req_inst_mem_bw />{'W': [[8.0, 8.0], [8.0, 8.0], [8.0, 8.0]], 'I': [[8.0, 0.5], [480.0, 136.0], [136.0, 3.8]], 'O': [[8.0, 0.5], [480.0, 3.3], [3.3, 3.3]]}<req_mem_bw_bit_per_cycle_individual />{'W': [[8.0, 8.0], [8.0, 8.0], [8.0, 0]], 'I': [[8.0, 0.1], [120.0, 3.8], [3.8, 0]], 'O': [[8.0, 0.5], [480.0, 3.3], [3.3, 0]]}<req_mem_bw_bit_per_cycle_shared />{'W': [[8.0, 8.0], [131.3, 491.8], [11.8, 3.3]], 'I': [[8.0, 0.1], [131.3, 491.8], [11.8, 3.3]], 'O': [[8.0, 0.5], [131.3, 491.8], [11.8, 3.3]]}<output_distinguish />[('psum', 'fsum'), ('fsum', 'fsum'), ('fsum', 'fsum')]<mem_bw_requirement_meet />{'W': [[True, True], [True, False], [True, True]], 'I': [[True, True], [True, False], [True, True]], 'O': [[True, True], [True, False], [True, True]]}<trans_time_ideal />{'W': [[1, 1, 589824], [64, 64, 9216], [589824, 589824, 1]], 'I': [[1, 1, 589824], [1024, 1024, 576], [589824, 589824, 1]], 'O': [[1, 1, 589824], [1024, 147456, 4], [589824, 589824, 1]]}<trans_time_real />{'W': [[0, 1, 589824], [[8, 64, 9216], [1, 64, 9216]], [[12288, 589824, 1], [2304, 589824, 1]]], 'I': [[0, 1, 589824], [[2, 1024, 576], [320, 1024, 576]], [[5803, 589824, 1], [1088, 589824, 1]]], 'O': [[0, 1, 589824], [[8, 147456, 4], [1280, 147456, 4]], [[5120, 589824, 1], [960, 589824, 1]]]}<single_stall_cycle />{'W': [[-1], [-56, -63], [-577536, -587520]], 'I': [[-1], [-1022, -704], [-584021, -588736]], 'O': [[-1], [-1016, 256], [-584704, -588864]]}<single_stall_count />{'W': [589823, 9215, 0], 'I': [589823, 575, 0], 'O': [589824, 4, 1]}<mem_compute_overlap_cc_for_shared_mem />{0: {'W': [0, 0], 'I': [0, 0], 'O': [5120, 0]}, 1: {'W': [73720, 0], 'I': [184000, 0], 'O': [4096, 5120]}}<mem_compute_overlap_stall_for_shared_mem_LH />{0: [[-589824, -589824], [-584704, -589824]], 1: [[-332104, -589824], [-585728, -584704]]}</latency_deep_analysis></mem_stalling></latency></performance><area><total_area />120.1<mem_area />114.9<mem_area_percentage />95.7 %</area></results><elapsed_time_second />3.655</simulation></root>