<root><simulation><result_generated_time />2023-05-17 20:18:31<layer><layer_spec />{'B': 1, 'K': 64, 'C': 64, 'OY': 300, 'OX': 300, 'IY': 302, 'IX': 302, 'FY': 3, 'FX': 3, 'SY': 1, 'SX': 1, 'SFY': 1, 'SFX': 1, 'G': 1}<im2col_enable />False<total_MAC_operation />3317760000<total_data_size_element />{'W': 36864, 'I': 5837056, 'O': 5760000}<total_data_reuse />{'W': 90000, 'I': 568.3961229770624, 'O': 576}</layer><search_engine><mem_hierarchy_search><mode />fixed<mem_scheme_index />1/1</mem_hierarchy_search><spatial_mapping_search><mode />greedy mapping with hint<spatial_utilization_threshold />0.0<unrolling_scheme_index />1/1</spatial_mapping_search><temporal_mapping_search><mode />loma search<valid_temporal_mapping_found />40320</temporal_mapping_search></search_engine><hw_spec><PE_array><precision_bit />{'W': 8, 'I': 8, 'O_partial': 8, 'O_final': 8}<MAC_array_size />{'Col': 8, 'Row': 8}</PE_array><memory_hierarchy><mem_name_in_the_hierarchy><W />['spad_32byte', 'buffer_2Mbyte', 'sram_big']<I />['spad_32byte', 'buffer_2Mbyte', 'sram_big']<O />['spad_32byte', 'buffer_2Mbyte', 'sram_big']</mem_name_in_the_hierarchy><mem_size_bit />{'W': [512, 8388608, 34359738368], 'I': [512, 8388608, 34359738368], 'O': [512, 8388608, 34359738368]}<mem_bw_bit_per_cycle_or_mem_wordlength />{'W': [[64, 64], [128, 128], [2048, 2048]], 'I': [[64, 64], [128, 128], [2048, 2048]], 'O': [[64, 64], [128, 128], [2048, 2048]]}<mem_access_energy_per_word />{'W': [[0.000336027, 0.000364555], [0.02631975, 0.0232271], [1.33185, 1.33185]], 'I': [[0.000336027, 0.000364555], [0.02631975, 0.0232271], [1.33185, 1.33185]], 'O': [[0.000336027, 0.000364555], [0.02631975, 0.0232271], [1.33185, 1.33185]]}<mem_type />{'W': ['dp_sb', 'dp_db', 'dp_sb'], 'I': ['dp_sb', 'dp_db', 'dp_sb'], 'O': ['dp_sb', 'dp_db', 'dp_sb']}<mem_share />{0: [('W', 'sram_big'), ('I', 'sram_big'), ('O', 'sram_big')], 1: [('W', 'buffer_2Mbyte'), ('I', 'buffer_2Mbyte'), ('O', 'buffer_2Mbyte')]}<mem_area_single_module />{'W': [0.000693826, 6.752825, 93.2871], 'I': [0.000693826, 6.752825, 93.2871], 'O': [0.000693826, 6.752825, 93.2871]}<mem_unroll />{'W': [64, 1, 1], 'I': [8, 1, 1], 'O': [8, 1, 1]}</memory_hierarchy></hw_spec><results><basic_info><spatial_unrolling><W />[[], [[('C', 8)], [('K', 8)]], [], []]<I />[[[], [('K', 8)]], [[('C', 8)], []], [], []]<O />[[[('C', 8)], []], [[], [('K', 8)]], [], []]<greedy_mapping />False</spatial_unrolling><temporal_mapping><W />[[('FX', 3), ('OX', 12), ('OX', 25), ('OY', 25)], [('K', 8), ('C', 8), ('FY', 3), ('OY', 12)], []]<I />[[('FX', 3)], [('OX', 12), ('OX', 25), ('OY', 25), ('K', 8), ('C', 8), ('FY', 3)], [('OY', 12)]]<O />[[('FX', 3)], [('OX', 12), ('OX', 25), ('OY', 25), ('K', 8), ('C', 8), ('FY', 3)], [('OY', 12)]]<fully_PE_level_output_stationary />False</temporal_mapping><data_reuse />{'W': [1.0, 7500, 12, 1], 'I': [8.0, 2.98, 23.84, 1.0], 'O': [8.0, 3, 24, 1]}<I_pr_diagonally_broadcast_or_fifo_effect />'I': [False, True, False, False]<used_mem_size_bit />{'W': [24, 294912, 294912], 'I': [24, 4174848, 46696448], 'O': [8, 3840000, 46080000], 'O_partial': [8, 3840000, 0], 'O_final': [0, 0, 46080000]}<actual_mem_utilization_individual />{'W': [0.05, 0.04, 0.0], 'I': [0.05, 0.5, 0.0], 'O': [0.02, 0.46, 0.0]}<actual_mem_utilization_shared />{'W': [0.05, 0.99, 0.0], 'I': [0.05, 0.99, 0.0], 'O': [0.02, 0.99, 0.0]}<effective_mem_size_bit />{'W': [24, 294912, 294912], 'I': [24, 4174848, 46696448], 'O': [8, 3840000, 3840000], 'O_partial': [8, 3840000, 0], 'O_final': [0, 0, 3840000]}<total_unit_count />{'W': [64, 64, 1, 1], 'I': [64, 8, 1, 1], 'O': [64, 8, 1, 1]}<unique_unit_count />{'W': [64, 64, 1, 1], 'I': [8, 8, 1, 1], 'O': [8, 8, 1, 1]}<duplicate_unit_count />{'W': [1.0, 1.0, 1.0, 1.0], 'I': [8.0, 1.0, 1.0, 1.0], 'O': [8.0, 1.0, 1.0, 1.0]}<mem_access_count_elem><W />[[3317760000, 442368], [442368, 36864], [36864, 0]]<I />[[414720000, 139161600], [139161600, 5837056], [5837056, 0]]<O />[[(408960000, 414720000), (138240000, 132480000)], [(132480000, 138240000), (5760000, 0)], [(0, 5760000), (0, 0)]]<O_partial />[[(408960000, 414720000), (138240000, 132480000)], [(132480000, 138240000), (0, 0)], [(0, 0), (0, 0)]]<O_final />[[(0, 0), (0, 0)], [(0, 0), (5760000, 0)], [(0, 5760000), (0, 0)]]</mem_access_count_elem><mem_access_count_word><W />[[414720000, 55296], [27648, 2304], [144, 0]]<I />[[51840000, 17395200], [8697600, 364816], [22801, 0]]<O />[[(51120000, 51840000), (17280000, 16560000)], [(8280000, 8640000), (360000, 0)], [(0, 22500), (0, 0)]]<O_partial />[([51120000, 51840000], [17280000, 16560000]), ([8280000, 8640000], [0, 0]), ([0, 0], [0, 0])]<O_final />[([0, 0], [0, 0]), ([0, 0], [360000, 0]), ([0, 22500], [0, 0])]</mem_access_count_word><mac_count><active />3317760000<idle />0</mac_count></basic_info><energy><total_energy />7253561202.4<mem_energy_breakdown><W />[139377.3, 781.2, 191.8]<I />[23761.1, 237392.3, 30367.5]<O />[47919.8, 428084.8, 29966.6]</mem_energy_breakdown><MAC_energy><active_MAC />7252623360.0<idle_MAC />0.0<total />7252623360.0</MAC_energy></energy><performance><mac_array_utilization><utilization_with_data_loading />0.9993<utilization_without_data_loading />1.0<utilization_spatial />1.0<utilization_temporal_with_data_loading />0.9993<mac_utilize_temporal_without_data_loading />1.0</mac_array_utilization><latency><latency_cycle_with_data_loading />51874922<latency_cycle_without_data_loading />51840000<ideal_computing_cycle />51840000<data_loading><load_cycle_total />34922<load_cycle_individual />{'W': [12, 2304, 0], 'I': [2, 32616, 0]}<load_cycle_combined />{'W': 2304, 'I': 32616}</data_loading><mem_stalling><mem_stall_cycle_total />0<mem_stall_cycle_individual />{'W': [[-51839999], [-51817500, -51789864], [-51840000, -51840000]], 'I': [[-51839999], [-51839997, -34559998], [-47161224, -47497582]], 'O': [[-51840000], [-51840000, -34560000], [-51480000, -51817500]]}<mem_stall_cycle_shared />{'W': [[-51839999], [-51817500, 0], [0, 0]], 'I': [[-51839999], [-51839997, 0], [0, 0]], 'O': [[-51840000], [-51840000, -34560000], [-51480000, -51817500]]}<latency_deep_analysis><data_size_each_level_unrolled />{'W': [24, 294912, 294912], 'I': [24, 4174848, 46696448], 'O': [8, 3840000, 46080000], 'O_partial': [8, 3840000, 0], 'O_final': [0, 0, 46080000]}<data_size_each_level_total />{'W': [1536, 294912, 294912], 'I': [192, 4174848, 46696448], 'O': [64, 3840000, 46080000]}<loop_cycles_each_level />{'W': [22500, 51840000, 51840000], 'I': [3, 4320000, 51840000], 'O': [3, 4320000, 51840000]}<top_ir_loop_size />{'W': [7500, 12, 1], 'I': [3, 3, 1], 'O': [3, 24, 1]}<req_aver_mem_bw />{'W': [[8.0, 0.0], [0.1, 0.0], [0.0, 0.0]], 'I': [[8.0, 8.0], [64.0, 1.0], [1.0, 0.9]], 'O': [[8.0, 2.7], [21.3, 0.9], [0.9, 0.9]]}<req_inst_mem_bw />{'W': [[8.0, 8.0], [512.0, 0.1], [0.1, 0.0]], 'I': [[8.0, 24.0], [192.0, 2.9], [2.9, 0.9]], 'O': [[8.0, 8.0], [64.0, 21.3], [21.3, 0.9]]}<req_mem_bw_bit_per_cycle_individual />{'W': [[8.0, 0.0], [0.1, 0.0], [0.0, 0]], 'I': [[8.0, 8.0], [64.0, 1.0], [1.0, 0]], 'O': [[8.0, 2.7], [21.3, 0.9], [0.9, 0]]}<req_mem_bw_bit_per_cycle_shared />{'W': [[8.0, 0.0], [86.3, 22.3], [1.0, 0.9]], 'I': [[8.0, 8.0], [86.3, 22.3], [1.0, 0.9]], 'O': [[8.0, 2.7], [86.3, 22.3], [1.0, 0.9]]}<output_distinguish />[('psum', 'psum'), ('psum', 'fsum'), ('fsum', 'fsum')]<mem_bw_requirement_meet />{'W': [[True, True], [True, True], [True, True]], 'I': [[True, True], [True, True], [True, True]], 'O': [[True, True], [True, True], [True, True]]}<trans_time_ideal />{'W': [[1, 1, 51840000], [22500, 22500, 2304], [51840000, 51840000, 1]], 'I': [[1, 1, 51840000], [3, 3, 17280000], [4320000, 4320000, 12]], 'O': [[1, 1, 51840000], [3, 3, 17280000], [4320000, 4320000, 12]]}<trans_time_real />{'W': [[0, 1, 51840000], [[0, 22500, 2304], [12, 22500, 2304]], [[2304, 51840000, 1], [144, 51840000, 1]]], 'I': [[0, 1, 51840000], [[0, 3, 17280000], [2, 3, 17280000]], [[32616, 4320000, 12], [2038, 4320000, 12]]], 'O': [[0, 1, 51840000], [[0, 3, 17280000], [0, 3, 17280000]], [[30000, 4320000, 12], [1875, 4320000, 12]]]}<single_stall_cycle />{'W': [[-1], [-22500, -22488], [-51837696, -51839856]], 'I': [[-1], [-3, -2], [-4287384, -4317962]], 'O': [[-1], [-3, -2], [-4290000, -4318125]]}<single_stall_count />{'W': [51839999, 2303, 0], 'I': [51839999, 17279999, 11], 'O': [51840000, 17280000, 12]}<mem_compute_overlap_cc_for_shared_mem />{0: {'W': [0, 0], 'I': [358776, 0], 'O': [360000, 0]}, 1: {'W': [27636, 0], 'I': [34559998, 358776], 'O': [0, 360000]}}<mem_compute_overlap_stall_for_shared_mem_LH />{0: [[-51481224, -51840000], [-51480000, -51840000]], 1: [[-17252366, -51481224], [-51840000, -51480000]]}</latency_deep_analysis></mem_stalling></latency></performance><area><total_area />100.1<mem_area />100.1<mem_area_percentage />100.0 %</area></results><elapsed_time_second />12.733</simulation></root>